{
  "version": "7",
  "dialect": "sqlite",
  "entries": [
    {
      "idx": 0,
      "version": "6",
      "when": 1733957131005,
      "tag": "0000_milky_iron_man",
      "breakpoints": true
    },
    {
      "idx": 1,
      "version": "6",
      "when": 1737430316579,
      "tag": "0001_burly_union_jack",
      "breakpoints": true
    },
    {
      "idx": 2,
      "version": "6",
      "when": 1737676343201,
      "tag": "0002_broken_clea",
      "breakpoints": true
    },
    {
      "idx": 3,
      "version": "6",
      "when": 1742325670797,
      "tag": "0003_dashing_turbo",
      "breakpoints": true
    },
    {
      "idx": 4,
      "version": "6",
      "when": 1744392120303,
      "tag": "0004_perpetual_miss_america",
      "breakpoints": true
    },
    {
      "idx": 5,
      "version": "6",
      "when": 1746681743705,
      "tag": "0005_gorgeous_cammi",
      "breakpoints": true
    },
    {
      "idx": 6,
      "version": "6",
      "when": 1747246898580,
      "tag": "0006_long_sauron",
      "breakpoints": true
    },
    {
      "idx": 7,
      "version": "6",
      "when": 1747867509179,
      "tag": "0007_fresh_mongoose",
      "breakpoints": true
    }
  ]
}