{
  "version": "5",
  "dialect": "sqlite",
  "entries": [
    {
      "idx": 0,
      "version": "5",
      "when": 1686750707329,
      "tag": "0000_sticky_mandrill",
      "breakpoints": false
    },
    {
      "idx": 1,
      "version": "5",
      "when": 1686796530381,
      "tag": "0001_eager_gladiator",
      "breakpoints": false
    },
    {
      "idx": 2,
      "version": "5",
      "when": 1686797457303,
      "tag": "0002_sparkling_agent_brand",
      "breakpoints": false
    }
  ]
}